py_visual_cobol/__init__.py
py_visual_cobol/constants/__init__.py
py_visual_cobol/constants/params.py
py_visual_cobol/helper/monitoring.py
py_visual_cobol/record_extractor.py
py_visual_cobol/utils/__init__.py
py_visual_cobol/utils/bytes_converter.py
py_visual_cobol/utils/segment_patterns_generator.py
py_visual_cobol-1.1.7.dist-info/LICENSE
py_visual_cobol-1.1.7.dist-info/METADATA
py_visual_cobol-1.1.7.dist-info/WHEEL
py_visual_cobol-1.1.7.dist-info/RECORD
