Metadata-Version: 2.1
Name: py-visual-cobol
Version: 1.1.7
Summary: Python script to parse and return records based on the record line. This script specifically handles microfile headers sequentially.
License: MIT
Author: Yassine Essadi
Author-email: yasine.esadi@gmail.com
Requires-Python: >=3.8,<3.12
Classifier: License :: OSI Approved :: MIT License
Classifier: Programming Language :: Python :: 3
Classifier: Programming Language :: Python :: 3.8
Classifier: Programming Language :: Python :: 3.9
Classifier: Programming Language :: Python :: 3.10
Classifier: Programming Language :: Python :: 3.11
